deltatask/__init__.py
deltatask/__main__.py
deltatask/models/__init__.py
deltatask/models/base.py
deltatask/models/tag.py
deltatask/models/todo.py
deltatask/repositories/__init__.py
deltatask/repositories/task_repository.py
deltatask/services/__init__.py
deltatask/services/obsidian_service.py
deltatask/services/task_service.py
deltatask/utils/__init__.py
iflow_mcp_deltatask-0.1.1.dist-info/licenses/LICENSE
iflow_mcp_deltatask-0.1.1.dist-info/METADATA
iflow_mcp_deltatask-0.1.1.dist-info/WHEEL
iflow_mcp_deltatask-0.1.1.dist-info/entry_points.txt
iflow_mcp_deltatask-0.1.1.dist-info/top_level.txt
iflow_mcp_deltatask-0.1.1.dist-info/RECORD
