Metadata-Version: 2.4
Name: iflow-mcp_deltatask
Version: 0.1.1
Summary: Add your description here
Author: DeltaTask Team
Requires-Python: >=3.8
License-File: LICENSE
Requires-Dist: mcp[cli]>=1.3.0
Requires-Dist: python-frontmatter>=1.1.0
Requires-Dist: sqlalchemy>=2.0.0
Dynamic: author
Dynamic: license-file
Dynamic: requires-python
